list.py
linked_lists_sd-0.0.1.dist-info/LICENSE
linked_lists_sd-0.0.1.dist-info/METADATA
linked_lists_sd-0.0.1.dist-info/WHEEL
linked_lists_sd-0.0.1.dist-info/top_level.txt
linked_lists_sd-0.0.1.dist-info/RECORD
