Metadata-Version: 2.1
Name: linked-lists-sd
Version: 0.0.1
Summary: Helps you with different kinds of Linked Lists
Home-page: https://github.com/sardug10/lists
Author: SARTHAK DUGGAL
Author-email: duggal.sarthak12@gmail.com
License: UNKNOWN
Platform: UNKNOWN
Classifier: Programming Language :: Python :: 3
Classifier: Programming Language :: Python :: 3.6
Classifier: Programming Language :: Python :: 3.7
Classifier: Programming Language :: Python :: 3.8
Classifier: License :: OSI Approved :: MIT License
Classifier: Operating System :: OS Independent
Provides-Extra: dev
Requires-Dist: pytest (>=3.7) ; extra == 'dev'
